coinsight/__init__.py
coinsight-0.0.0.dist-info/LICENSE
coinsight-0.0.0.dist-info/METADATA
coinsight-0.0.0.dist-info/WHEEL
coinsight-0.0.0.dist-info/top_level.txt
coinsight-0.0.0.dist-info/RECORD
